pycharts/__init__.py
pycharts/base.py
pycharts/clients.py
pycharts/exceptions.py
pycharts-0.1.4.dist-info/DESCRIPTION.rst
pycharts-0.1.4.dist-info/METADATA
pycharts-0.1.4.dist-info/RECORD
pycharts-0.1.4.dist-info/WHEEL
pycharts-0.1.4.dist-info/metadata.json
pycharts-0.1.4.dist-info/top_level.txt
